topsis.py
102003766_topsis-0.0.1.dist-info/LICENSE.txt
102003766_topsis-0.0.1.dist-info/METADATA
102003766_topsis-0.0.1.dist-info/WHEEL
102003766_topsis-0.0.1.dist-info/top_level.txt
102003766_topsis-0.0.1.dist-info/RECORD
