Metadata-Version: 2.1
Name: 102003766-topsis
Version: 0.0.1
Summary: Multiple Criteria Decision Making
Author: Sahil Chhabra
Author-email: sahil.chh718@gmail.com
Classifier: Programming Language :: Python :: 3
Classifier: Programming Language :: Python :: 3.6
Classifier: Programming Language :: Python :: 3.7
Classifier: Operating System :: OS Independent
License-File: LICENSE.txt
